darksky/__init__.py
darksky/data.py
darksky/forecast.py
darkskylib-0.3.91.dist-info/DESCRIPTION.rst
darkskylib-0.3.91.dist-info/METADATA
darkskylib-0.3.91.dist-info/RECORD
darkskylib-0.3.91.dist-info/WHEEL
darkskylib-0.3.91.dist-info/metadata.json
darkskylib-0.3.91.dist-info/top_level.txt
darkskylib-0.3.91.dist-info/zip-safe
