Metadata-Version: 1.1
Name: darkskylib
Version: 0.3.91
Summary: The Dark Sky API wrapper
Home-page: https://github.com/lukaskubis/darkskylib
Author: Lukas Kubis
Author-email: contact@lukaskubis.com
License: MIT
Keywords: darksky dark-sky dark sky forecast home weather home-weather weather-station
Platform: UNKNOWN
Classifier: Development Status :: 4 - Beta
Classifier: License :: OSI Approved :: MIT License
Classifier: Topic :: Scientific/Engineering :: Atmospheric Science
Classifier: Topic :: Home Automation
Classifier: Programming Language :: Python :: 2
Classifier: Programming Language :: Python :: 2.6
Classifier: Programming Language :: Python :: 2.7
Classifier: Programming Language :: Python :: 3
Classifier: Programming Language :: Python :: 3.3
Classifier: Programming Language :: Python :: 3.4
Classifier: Programming Language :: Python :: 3.5
Classifier: Programming Language :: Python :: 3.6
Classifier: Programming Language :: Python :: 3.7
Classifier: Operating System :: OS Independent
